{
  "_links": {
    "self": {
      "href": "http:\/\/default\/product\/1?_format=hal_json"
    },
    "type": {
      "href": "http:\/\/drupal.org\/rest\/type\/commerce_product\/default"
    },
    "http:\/\/drupal.org\/rest\/relation\/commerce_product\/default\/uid": [
      {
        "href": "http:\/\/default\/user\/1?_format=hal_json",
        "lang": "en"
      }
    ],
    "http:\/\/drupal.org\/rest\/relation\/commerce_product\/default\/stores": [
      {
        "href": "http:\/\/default\/store\/1?_format=hal_json"
      }
    ],
    "http:\/\/drupal.org\/rest\/relation\/commerce_product\/default\/variations": [
      {
        "href": ""
      },
      {
        "href": ""
      }
    ]
  },
  "product_id": [
    {
      "value": "1"
    }
  ],
  "uuid": [
    {
      "value": "d4e7fc56-a594-4abe-a236-3e2c328ffdff"
    }
  ],
  "langcode": [
    {
      "value": "en",
      "lang": "en"
    }
  ],
  "type": [
    {
      "target_id": "default"
    }
  ],
  "_embedded": {
    "http:\/\/drupal.org\/rest\/relation\/commerce_product\/default\/uid": [
      {
        "_links": {
          "self": {
            "href": "http:\/\/default\/user\/1?_format=hal_json"
          },
          "type": {
            "href": "http:\/\/drupal.org\/rest\/type\/user\/user"
          }
        },
        "uuid": [
          {
            "value": "a4856335-4dbe-422f-96e7-6ea363f181f9"
          }
        ],
        "lang": "en"
      }
    ],
    "http:\/\/drupal.org\/rest\/relation\/commerce_product\/default\/stores": [
      {
        "_links": {
          "self": {
            "href": "http:\/\/default\/store\/1?_format=hal_json"
          },
          "type": {
            "href": "http:\/\/drupal.org\/rest\/type\/commerce_store\/online"
          }
        },
        "uuid": [
          {
            "value": "40a0a780-7211-4cd0-9b87-512cc6e7d69f"
          }
        ]
      }
    ],
    "http:\/\/drupal.org\/rest\/relation\/commerce_product\/default\/variations": [
      {
        "_links": {
          "self": {
            "href": ""
          },
          "type": {
            "href": "http:\/\/drupal.org\/rest\/type\/commerce_product_variation\/default"
          }
        },
        "uuid": [
          {
            "value": "5730dfb3-e8ec-4566-bcd1-36e94aafcc45"
          }
        ]
      },
      {
        "_links": {
          "self": {
            "href": ""
          },
          "type": {
            "href": "http:\/\/drupal.org\/rest\/type\/commerce_product_variation\/default"
          }
        },
        "uuid": [
          {
            "value": "d3203c55-6b57-468c-b724-47eecdb8e109"
          }
        ]
      }
    ]
  },
  "title": [
    {
      "value": "test",
      "lang": "en"
    }
  ],
  "status": [
    {
      "value": "1",
      "lang": "en"
    }
  ],
  "created": [
    {
      "value": "1476937437",
      "lang": "en"
    }
  ],
  "changed": [
    {
      "value": "1476940727",
      "lang": "en"
    }
  ],
  "default_langcode": [
    {
      "value": "1",
      "lang": "en"
    }
  ],
  "body": [
    {
      "value": "<p>asdfadd<\/p>\r\n",
      "format": "basic_html",
      "summary": "",
      "lang": "en"
    }
  ]
}
